odoo/addons/sale_margin_delivered/README.rst
odoo/addons/sale_margin_delivered/__init__.py
odoo/addons/sale_margin_delivered/__manifest__.py
odoo/addons/sale_margin_delivered/i18n/es.po
odoo/addons/sale_margin_delivered/i18n/sale_margin_delivered.pot
odoo/addons/sale_margin_delivered/models/__init__.py
odoo/addons/sale_margin_delivered/models/sale_margin.py
odoo/addons/sale_margin_delivered/readme/CONFIGURE.rst
odoo/addons/sale_margin_delivered/readme/CONTRIBUTORS.rst
odoo/addons/sale_margin_delivered/readme/DESCRIPTION.rst
odoo/addons/sale_margin_delivered/readme/USAGE.rst
odoo/addons/sale_margin_delivered/reports/__init__.py
odoo/addons/sale_margin_delivered/reports/sale_report.py
odoo/addons/sale_margin_delivered/static/description/icon.png
odoo/addons/sale_margin_delivered/static/description/index.html
odoo/addons/sale_margin_delivered/tests/__init__.py
odoo/addons/sale_margin_delivered/tests/test_sale_margin_delivered.py
odoo/addons/sale_margin_delivered/views/sale_margin_delivered_view.xml
odoo11_addon_sale_margin_delivered-11.0.1.0.0.99.dev11.dist-info/METADATA
odoo11_addon_sale_margin_delivered-11.0.1.0.0.99.dev11.dist-info/WHEEL
odoo11_addon_sale_margin_delivered-11.0.1.0.0.99.dev11.dist-info/top_level.txt
odoo11_addon_sale_margin_delivered-11.0.1.0.0.99.dev11.dist-info/RECORD
